astro_parsnip-1.4.2.data/scripts/parsnip_build_plasticc_combined
astro_parsnip-1.4.2.data/scripts/parsnip_predict
astro_parsnip-1.4.2.data/scripts/parsnip_train
parsnip/__init__.py
parsnip/classifier.py
parsnip/instruments.py
parsnip/light_curve.py
parsnip/parsnip.py
parsnip/plotting.py
parsnip/settings.py
parsnip/sncosmo.py
parsnip/utils.py
parsnip/models/plasticc.pt
parsnip/models/plasticc_photoz.pt
parsnip/models/ps1.pt
astro_parsnip-1.4.2.dist-info/LICENSE
astro_parsnip-1.4.2.dist-info/METADATA
astro_parsnip-1.4.2.dist-info/WHEEL
astro_parsnip-1.4.2.dist-info/top_level.txt
astro_parsnip-1.4.2.dist-info/RECORD
