Metadata-Version: 2.1
Name: astro-parsnip
Version: 1.4.2
Summary: Deep generative modeling of astronomical transient light curves
Home-page: https://github.com/kboone/parsnip
Author: Kyle Boone
Author-email: kyboone@uw.edu
Classifier: Programming Language :: Python :: 3
Classifier: License :: OSI Approved :: MIT License
Classifier: Operating System :: OS Independent
Requires-Python: >=3.6
License-File: LICENSE
Requires-Dist: astropy
Requires-Dist: extinction
Requires-Dist: lcdata >=1.1.1
Requires-Dist: lightgbm <3,>=2.3.1
Requires-Dist: matplotlib
Requires-Dist: numpy
Requires-Dist: scikit-learn
Requires-Dist: scipy
Requires-Dist: sncosmo >=2.6
Requires-Dist: torch
Requires-Dist: tqdm
Provides-Extra: docs
Requires-Dist: numpy ; extra == 'docs'
Requires-Dist: sphinx ; extra == 'docs'
Requires-Dist: sphinx-rtd-theme ; extra == 'docs'
Requires-Dist: pillow ; extra == 'docs'
Requires-Dist: numpydoc ; extra == 'docs'
